[
  {
    "id": "a_q_Data_Scientist_0_high",
    "question_id": "q_Data_Scientist_0",
    "content": "The key concept behind this is...\n\nTo implement this, you would...\n\nFor better performance, consider...\n\n",
    "audio_source": null,
    "confidence": 0.95,
    "created_at": "2025-04-03T21:45:16.730831"
  },
  {
    "id": "a_q_Data_Scientist_0_medium",
    "question_id": "q_Data_Scientist_0",
    "content": "For better performance, consider...\n\n",
    "audio_source": null,
    "confidence": 0.8,
    "created_at": "2025-04-03T21:45:16.795660"
  },
  {
    "id": "a_q_Data_Scientist_0_low",
    "question_id": "q_Data_Scientist_0",
    "content": "",
    "audio_source": null,
    "confidence": 0.6,
    "created_at": "2025-04-03T21:45:16.798924"
  },
  {
    "id": "a_q_Data_Scientist_1_high",
    "question_id": "q_Data_Scientist_1",
    "content": "The key concept behind this is...\n\nTo implement this, you would...\n\nFor better performance, consider...\n\n",
    "audio_source": null,
    "confidence": 0.95,
    "created_at": "2025-04-03T21:45:16.802134"
  },
  {
    "id": "a_q_Data_Scientist_1_medium",
    "question_id": "q_Data_Scientist_1",
    "content": "For better performance, consider...\n\n",
    "audio_source": null,
    "confidence": 0.8,
    "created_at": "2025-04-03T21:45:16.804679"
  },
  {
    "id": "a_q_Data_Scientist_1_low",
    "question_id": "q_Data_Scientist_1",
    "content": "",
    "audio_source": null,
    "confidence": 0.6,
    "created_at": "2025-04-03T21:45:16.807375"
  },
  {
    "id": "a_q_Data_Scientist_2_high",
    "question_id": "q_Data_Scientist_2",
    "content": "The key concept behind this is...\n\nTo implement this, you would...\n\nFor better performance, consider...\n\n",
    "audio_source": null,
    "confidence": 0.95,
    "created_at": "2025-04-03T21:45:16.809785"
  },
  {
    "id": "a_q_Data_Scientist_2_medium",
    "question_id": "q_Data_Scientist_2",
    "content": "For better performance, consider...\n\n",
    "audio_source": null,
    "confidence": 0.8,
    "created_at": "2025-04-03T21:45:16.812070"
  },
  {
    "id": "a_q_Data_Scientist_2_low",
    "question_id": "q_Data_Scientist_2",
    "content": "",
    "audio_source": null,
    "confidence": 0.6,
    "created_at": "2025-04-03T21:45:16.813108"
  },
  {
    "id": "a_q_Data_Scientist_3_high",
    "question_id": "q_Data_Scientist_3",
    "content": "The key concept behind this is...\n\nTo implement this, you would...\n\nFor better performance, consider...\n\n",
    "audio_source": null,
    "confidence": 0.95,
    "created_at": "2025-04-03T21:45:16.813108"
  },
  {
    "id": "a_q_Data_Scientist_3_medium",
    "question_id": "q_Data_Scientist_3",
    "content": "For better performance, consider...\n\n",
    "audio_source": null,
    "confidence": 0.8,
    "created_at": "2025-04-03T21:45:16.818607"
  },
  {
    "id": "a_q_Data_Scientist_3_low",
    "question_id": "q_Data_Scientist_3",
    "content": "",
    "audio_source": null,
    "confidence": 0.6,
    "created_at": "2025-04-03T21:45:16.820682"
  },
  {
    "id": "a_q_Data_Scientist_4_high",
    "question_id": "q_Data_Scientist_4",
    "content": "The key concept behind this is...\n\nTo implement this, you would...\n\nFor better performance, consider...\n\n",
    "audio_source": null,
    "confidence": 0.95,
    "created_at": "2025-04-03T21:45:16.820682"
  },
  {
    "id": "a_q_Data_Scientist_4_medium",
    "question_id": "q_Data_Scientist_4",
    "content": "For better performance, consider...\n\n",
    "audio_source": null,
    "confidence": 0.8,
    "created_at": "2025-04-03T21:45:16.824677"
  },
  {
    "id": "a_q_Data_Scientist_4_low",
    "question_id": "q_Data_Scientist_4",
    "content": "",
    "audio_source": null,
    "confidence": 0.6,
    "created_at": "2025-04-03T21:45:16.828517"
  },
  {
    "id": "a_q_Data_Scientist_5_high",
    "question_id": "q_Data_Scientist_5",
    "content": "The key concept behind this is...\n\nTo implement this, you would...\n\nFor better performance, consider...\n\n",
    "audio_source": null,
    "confidence": 0.95,
    "created_at": "2025-04-03T21:45:16.829576"
  },
  {
    "id": "a_q_Data_Scientist_5_medium",
    "question_id": "q_Data_Scientist_5",
    "content": "For better performance, consider...\n\n",
    "audio_source": null,
    "confidence": 0.8,
    "created_at": "2025-04-03T21:45:16.832067"
  },
  {
    "id": "a_q_Data_Scientist_5_low",
    "question_id": "q_Data_Scientist_5",
    "content": "",
    "audio_source": null,
    "confidence": 0.6,
    "created_at": "2025-04-03T21:45:16.835265"
  },
  {
    "id": "a_q_Data_Scientist_6_high",
    "question_id": "q_Data_Scientist_6",
    "content": "The key concept behind this is...\n\nTo implement this, you would...\n\nFor better performance, consider...\n\n",
    "audio_source": null,
    "confidence": 0.95,
    "created_at": "2025-04-03T21:45:16.836733"
  },
  {
    "id": "a_q_Data_Scientist_6_medium",
    "question_id": "q_Data_Scientist_6",
    "content": "For better performance, consider...\n\n",
    "audio_source": null,
    "confidence": 0.8,
    "created_at": "2025-04-03T21:45:16.836733"
  },
  {
    "id": "a_q_Data_Scientist_6_low",
    "question_id": "q_Data_Scientist_6",
    "content": "",
    "audio_source": null,
    "confidence": 0.6,
    "created_at": "2025-04-03T21:45:16.836733"
  },
  {
    "id": "a_q_Data_Scientist_7_high",
    "question_id": "q_Data_Scientist_7",
    "content": "The key concept behind this is...\n\nTo implement this, you would...\n\nFor better performance, consider...\n\n",
    "audio_source": null,
    "confidence": 0.95,
    "created_at": "2025-04-03T21:45:16.842720"
  },
  {
    "id": "a_q_Data_Scientist_7_medium",
    "question_id": "q_Data_Scientist_7",
    "content": "For better performance, consider...\n\n",
    "audio_source": null,
    "confidence": 0.8,
    "created_at": "2025-04-03T21:45:16.842720"
  },
  {
    "id": "a_q_Data_Scientist_7_low",
    "question_id": "q_Data_Scientist_7",
    "content": "",
    "audio_source": null,
    "confidence": 0.6,
    "created_at": "2025-04-03T21:45:16.842720"
  },
  {
    "id": "a_q_Data_Scientist_8_high",
    "question_id": "q_Data_Scientist_8",
    "content": "The key concept behind this is...\n\nTo implement this, you would...\n\nFor better performance, consider...\n\n",
    "audio_source": null,
    "confidence": 0.95,
    "created_at": "2025-04-03T21:45:16.850306"
  },
  {
    "id": "a_q_Data_Scientist_8_medium",
    "question_id": "q_Data_Scientist_8",
    "content": "For better performance, consider...\n\n",
    "audio_source": null,
    "confidence": 0.8,
    "created_at": "2025-04-03T21:45:16.851865"
  },
  {
    "id": "a_q_Data_Scientist_8_low",
    "question_id": "q_Data_Scientist_8",
    "content": "",
    "audio_source": null,
    "confidence": 0.6,
    "created_at": "2025-04-03T21:45:16.855077"
  },
  {
    "id": "a_q_Data_Scientist_9_high",
    "question_id": "q_Data_Scientist_9",
    "content": "The key concept behind this is...\n\nTo implement this, you would...\n\nFor better performance, consider...\n\n",
    "audio_source": null,
    "confidence": 0.95,
    "created_at": "2025-04-03T21:45:16.857077"
  },
  {
    "id": "a_q_Data_Scientist_9_medium",
    "question_id": "q_Data_Scientist_9",
    "content": "For better performance, consider...\n\n",
    "audio_source": null,
    "confidence": 0.8,
    "created_at": "2025-04-03T21:45:16.859562"
  },
  {
    "id": "a_q_Data_Scientist_9_low",
    "question_id": "q_Data_Scientist_9",
    "content": "",
    "audio_source": null,
    "confidence": 0.6,
    "created_at": "2025-04-03T21:45:16.861253"
  },
  {
    "id": "a_q_Data_Scientist_10_high",
    "question_id": "q_Data_Scientist_10",
    "content": "The key concept behind this is...\n\nTo implement this, you would...\n\nFor better performance, consider...\n\n",
    "audio_source": null,
    "confidence": 0.95,
    "created_at": "2025-04-03T21:45:16.863374"
  },
  {
    "id": "a_q_Data_Scientist_10_medium",
    "question_id": "q_Data_Scientist_10",
    "content": "For better performance, consider...\n\n",
    "audio_source": null,
    "confidence": 0.8,
    "created_at": "2025-04-03T21:45:16.866164"
  },
  {
    "id": "a_q_Data_Scientist_10_low",
    "question_id": "q_Data_Scientist_10",
    "content": "",
    "audio_source": null,
    "confidence": 0.6,
    "created_at": "2025-04-03T21:45:16.868389"
  },
  {
    "id": "a_q_Data_Scientist_11_high",
    "question_id": "q_Data_Scientist_11",
    "content": "The key concept behind this is...\n\nTo implement this, you would...\n\nFor better performance, consider...\n\n",
    "audio_source": null,
    "confidence": 0.95,
    "created_at": "2025-04-03T21:45:16.870389"
  },
  {
    "id": "a_q_Data_Scientist_11_medium",
    "question_id": "q_Data_Scientist_11",
    "content": "For better performance, consider...\n\n",
    "audio_source": null,
    "confidence": 0.8,
    "created_at": "2025-04-03T21:45:16.873180"
  },
  {
    "id": "a_q_Data_Scientist_11_low",
    "question_id": "q_Data_Scientist_11",
    "content": "",
    "audio_source": null,
    "confidence": 0.6,
    "created_at": "2025-04-03T21:45:16.874423"
  },
  {
    "id": "a_q_Data_Scientist_12_high",
    "question_id": "q_Data_Scientist_12",
    "content": "The key concept behind this is...\n\nTo implement this, you would...\n\nFor better performance, consider...\n\n",
    "audio_source": null,
    "confidence": 0.95,
    "created_at": "2025-04-03T21:45:16.876430"
  },
  {
    "id": "a_q_Data_Scientist_12_medium",
    "question_id": "q_Data_Scientist_12",
    "content": "For better performance, consider...\n\n",
    "audio_source": null,
    "confidence": 0.8,
    "created_at": "2025-04-03T21:45:16.879751"
  },
  {
    "id": "a_q_Data_Scientist_12_low",
    "question_id": "q_Data_Scientist_12",
    "content": "",
    "audio_source": null,
    "confidence": 0.6,
    "created_at": "2025-04-03T21:45:16.881942"
  },
  {
    "id": "a_q_Data_Scientist_13_high",
    "question_id": "q_Data_Scientist_13",
    "content": "The key concept behind this is...\n\nTo implement this, you would...\n\nFor better performance, consider...\n\n",
    "audio_source": null,
    "confidence": 0.95,
    "created_at": "2025-04-03T21:45:16.884282"
  },
  {
    "id": "a_q_Data_Scientist_13_medium",
    "question_id": "q_Data_Scientist_13",
    "content": "For better performance, consider...\n\n",
    "audio_source": null,
    "confidence": 0.8,
    "created_at": "2025-04-03T21:45:16.886042"
  },
  {
    "id": "a_q_Data_Scientist_13_low",
    "question_id": "q_Data_Scientist_13",
    "content": "",
    "audio_source": null,
    "confidence": 0.6,
    "created_at": "2025-04-03T21:45:16.886042"
  },
  {
    "id": "a_q_Data_Scientist_14_high",
    "question_id": "q_Data_Scientist_14",
    "content": "The key concept behind this is...\n\nTo implement this, you would...\n\nFor better performance, consider...\n\n",
    "audio_source": null,
    "confidence": 0.95,
    "created_at": "2025-04-03T21:45:16.890779"
  },
  {
    "id": "a_q_Data_Scientist_14_medium",
    "question_id": "q_Data_Scientist_14",
    "content": "For better performance, consider...\n\n",
    "audio_source": null,
    "confidence": 0.8,
    "created_at": "2025-04-03T21:45:16.893780"
  },
  {
    "id": "a_q_Data_Scientist_14_low",
    "question_id": "q_Data_Scientist_14",
    "content": "",
    "audio_source": null,
    "confidence": 0.6,
    "created_at": "2025-04-03T21:45:16.896107"
  },
  {
    "id": "a_q_Data_Scientist_15_high",
    "question_id": "q_Data_Scientist_15",
    "content": "The key concept behind this is...\n\nTo implement this, you would...\n\nFor better performance, consider...\n\n",
    "audio_source": null,
    "confidence": 0.95,
    "created_at": "2025-04-03T21:45:16.897596"
  },
  {
    "id": "a_q_Data_Scientist_15_medium",
    "question_id": "q_Data_Scientist_15",
    "content": "For better performance, consider...\n\n",
    "audio_source": null,
    "confidence": 0.8,
    "created_at": "2025-04-03T21:45:16.900480"
  },
  {
    "id": "a_q_Data_Scientist_15_low",
    "question_id": "q_Data_Scientist_15",
    "content": "",
    "audio_source": null,
    "confidence": 0.6,
    "created_at": "2025-04-03T21:45:16.902442"
  },
  {
    "id": "a_q_Data_Scientist_16_high",
    "question_id": "q_Data_Scientist_16",
    "content": "The key concept behind this is...\n\nTo implement this, you would...\n\nFor better performance, consider...\n\n",
    "audio_source": null,
    "confidence": 0.95,
    "created_at": "2025-04-03T21:45:16.903496"
  },
  {
    "id": "a_q_Data_Scientist_16_medium",
    "question_id": "q_Data_Scientist_16",
    "content": "For better performance, consider...\n\n",
    "audio_source": null,
    "confidence": 0.8,
    "created_at": "2025-04-03T21:45:16.905968"
  },
  {
    "id": "a_q_Data_Scientist_16_low",
    "question_id": "q_Data_Scientist_16",
    "content": "",
    "audio_source": null,
    "confidence": 0.6,
    "created_at": "2025-04-03T21:45:16.905968"
  },
  {
    "id": "a_q_Data_Scientist_17_high",
    "question_id": "q_Data_Scientist_17",
    "content": "The key concept behind this is...\n\nTo implement this, you would...\n\nFor better performance, consider...\n\n",
    "audio_source": null,
    "confidence": 0.95,
    "created_at": "2025-04-03T21:45:16.909896"
  },
  {
    "id": "a_q_Data_Scientist_17_medium",
    "question_id": "q_Data_Scientist_17",
    "content": "For better performance, consider...\n\n",
    "audio_source": null,
    "confidence": 0.8,
    "created_at": "2025-04-03T21:45:16.909896"
  },
  {
    "id": "a_q_Data_Scientist_17_low",
    "question_id": "q_Data_Scientist_17",
    "content": "",
    "audio_source": null,
    "confidence": 0.6,
    "created_at": "2025-04-03T21:45:16.915464"
  },
  {
    "id": "a_q_Data_Scientist_18_high",
    "question_id": "q_Data_Scientist_18",
    "content": "The key concept behind this is...\n\nTo implement this, you would...\n\nFor better performance, consider...\n\n",
    "audio_source": null,
    "confidence": 0.95,
    "created_at": "2025-04-03T21:45:16.915464"
  },
  {
    "id": "a_q_Data_Scientist_18_medium",
    "question_id": "q_Data_Scientist_18",
    "content": "For better performance, consider...\n\n",
    "audio_source": null,
    "confidence": 0.8,
    "created_at": "2025-04-03T21:45:16.917883"
  },
  {
    "id": "a_q_Data_Scientist_18_low",
    "question_id": "q_Data_Scientist_18",
    "content": "",
    "audio_source": null,
    "confidence": 0.6,
    "created_at": "2025-04-03T21:45:16.921612"
  },
  {
    "id": "a_q_Data_Scientist_19_high",
    "question_id": "q_Data_Scientist_19",
    "content": "The key concept behind this is...\n\nTo implement this, you would...\n\nFor better performance, consider...\n\n",
    "audio_source": null,
    "confidence": 0.95,
    "created_at": "2025-04-03T21:45:16.923409"
  },
  {
    "id": "a_q_Data_Scientist_19_medium",
    "question_id": "q_Data_Scientist_19",
    "content": "For better performance, consider...\n\n",
    "audio_source": null,
    "confidence": 0.8,
    "created_at": "2025-04-03T21:45:16.925313"
  },
  {
    "id": "a_q_Data_Scientist_19_low",
    "question_id": "q_Data_Scientist_19",
    "content": "",
    "audio_source": null,
    "confidence": 0.6,
    "created_at": "2025-04-03T21:45:16.928581"
  },
  {
    "id": "a_q_Data_Scientist_20_high",
    "question_id": "q_Data_Scientist_20",
    "content": "In my previous role at XYZ company, we faced a situation where...\n\nMy task was to...\n\nTo address this, I...\n\nThe outcome was...\n\n",
    "audio_source": null,
    "confidence": 0.95,
    "created_at": "2025-04-03T21:45:16.929640"
  },
  {
    "id": "a_q_Data_Scientist_20_medium",
    "question_id": "q_Data_Scientist_20",
    "content": "To address this, I...\n\n",
    "audio_source": null,
    "confidence": 0.8,
    "created_at": "2025-04-03T21:45:16.929640"
  },
  {
    "id": "a_q_Data_Scientist_20_low",
    "question_id": "q_Data_Scientist_20",
    "content": "",
    "audio_source": null,
    "confidence": 0.6,
    "created_at": "2025-04-03T21:45:16.934316"
  },
  {
    "id": "a_q_Data_Scientist_21_high",
    "question_id": "q_Data_Scientist_21",
    "content": "In my previous role at XYZ company, we faced a situation where...\n\nMy task was to...\n\nTo address this, I...\n\nThe outcome was...\n\n",
    "audio_source": null,
    "confidence": 0.95,
    "created_at": "2025-04-03T21:45:16.934316"
  },
  {
    "id": "a_q_Data_Scientist_21_medium",
    "question_id": "q_Data_Scientist_21",
    "content": "To address this, I...\n\n",
    "audio_source": null,
    "confidence": 0.8,
    "created_at": "2025-04-03T21:45:16.938898"
  },
  {
    "id": "a_q_Data_Scientist_21_low",
    "question_id": "q_Data_Scientist_21",
    "content": "",
    "audio_source": null,
    "confidence": 0.6,
    "created_at": "2025-04-03T21:45:16.941695"
  },
  {
    "id": "a_q_Data_Scientist_22_high",
    "question_id": "q_Data_Scientist_22",
    "content": "In my previous role at XYZ company, we faced a situation where...\n\nMy task was to...\n\nTo address this, I...\n\nThe outcome was...\n\n",
    "audio_source": null,
    "confidence": 0.95,
    "created_at": "2025-04-03T21:45:16.943682"
  },
  {
    "id": "a_q_Data_Scientist_22_medium",
    "question_id": "q_Data_Scientist_22",
    "content": "To address this, I...\n\n",
    "audio_source": null,
    "confidence": 0.8,
    "created_at": "2025-04-03T21:45:16.945548"
  },
  {
    "id": "a_q_Data_Scientist_22_low",
    "question_id": "q_Data_Scientist_22",
    "content": "",
    "audio_source": null,
    "confidence": 0.6,
    "created_at": "2025-04-03T21:45:16.947388"
  },
  {
    "id": "a_q_Data_Scientist_23_high",
    "question_id": "q_Data_Scientist_23",
    "content": "In my previous role at XYZ company, we faced a situation where...\n\nMy task was to...\n\nTo address this, I...\n\nThe outcome was...\n\n",
    "audio_source": null,
    "confidence": 0.95,
    "created_at": "2025-04-03T21:45:16.950422"
  },
  {
    "id": "a_q_Data_Scientist_23_medium",
    "question_id": "q_Data_Scientist_23",
    "content": "To address this, I...\n\n",
    "audio_source": null,
    "confidence": 0.8,
    "created_at": "2025-04-03T21:45:16.951815"
  },
  {
    "id": "a_q_Data_Scientist_23_low",
    "question_id": "q_Data_Scientist_23",
    "content": "",
    "audio_source": null,
    "confidence": 0.6,
    "created_at": "2025-04-03T21:45:16.951815"
  },
  {
    "id": "a_q_Data_Scientist_24_high",
    "question_id": "q_Data_Scientist_24",
    "content": "In my previous role at XYZ company, we faced a situation where...\n\nMy task was to...\n\nTo address this, I...\n\nThe outcome was...\n\n",
    "audio_source": null,
    "confidence": 0.95,
    "created_at": "2025-04-03T21:45:16.951815"
  },
  {
    "id": "a_q_Data_Scientist_24_medium",
    "question_id": "q_Data_Scientist_24",
    "content": "To address this, I...\n\n",
    "audio_source": null,
    "confidence": 0.8,
    "created_at": "2025-04-03T21:45:16.960265"
  },
  {
    "id": "a_q_Data_Scientist_24_low",
    "question_id": "q_Data_Scientist_24",
    "content": "",
    "audio_source": null,
    "confidence": 0.6,
    "created_at": "2025-04-03T21:45:16.961696"
  },
  {
    "id": "a_q_Data_Scientist_25_high",
    "question_id": "q_Data_Scientist_25",
    "content": "In my previous role at XYZ company, we faced a situation where...\n\nMy task was to...\n\nTo address this, I...\n\nThe outcome was...\n\n",
    "audio_source": null,
    "confidence": 0.95,
    "created_at": "2025-04-03T21:45:16.964076"
  },
  {
    "id": "a_q_Data_Scientist_25_medium",
    "question_id": "q_Data_Scientist_25",
    "content": "To address this, I...\n\n",
    "audio_source": null,
    "confidence": 0.8,
    "created_at": "2025-04-03T21:45:16.967057"
  },
  {
    "id": "a_q_Data_Scientist_25_low",
    "question_id": "q_Data_Scientist_25",
    "content": "",
    "audio_source": null,
    "confidence": 0.6,
    "created_at": "2025-04-03T21:45:16.968772"
  },
  {
    "id": "a_q_Data_Scientist_26_high",
    "question_id": "q_Data_Scientist_26",
    "content": "In my previous role at XYZ company, we faced a situation where...\n\nMy task was to...\n\nTo address this, I...\n\nThe outcome was...\n\n",
    "audio_source": null,
    "confidence": 0.95,
    "created_at": "2025-04-03T21:45:16.970029"
  },
  {
    "id": "a_q_Data_Scientist_26_medium",
    "question_id": "q_Data_Scientist_26",
    "content": "To address this, I...\n\n",
    "audio_source": null,
    "confidence": 0.8,
    "created_at": "2025-04-03T21:45:16.970029"
  },
  {
    "id": "a_q_Data_Scientist_26_low",
    "question_id": "q_Data_Scientist_26",
    "content": "",
    "audio_source": null,
    "confidence": 0.6,
    "created_at": "2025-04-03T21:45:16.976098"
  },
  {
    "id": "a_q_Data_Scientist_27_high",
    "question_id": "q_Data_Scientist_27",
    "content": "In my previous role at XYZ company, we faced a situation where...\n\nMy task was to...\n\nTo address this, I...\n\nThe outcome was...\n\n",
    "audio_source": null,
    "confidence": 0.95,
    "created_at": "2025-04-03T21:45:16.978125"
  },
  {
    "id": "a_q_Data_Scientist_27_medium",
    "question_id": "q_Data_Scientist_27",
    "content": "To address this, I...\n\n",
    "audio_source": null,
    "confidence": 0.8,
    "created_at": "2025-04-03T21:45:16.980254"
  },
  {
    "id": "a_q_Data_Scientist_27_low",
    "question_id": "q_Data_Scientist_27",
    "content": "",
    "audio_source": null,
    "confidence": 0.6,
    "created_at": "2025-04-03T21:45:16.980254"
  },
  {
    "id": "a_q_Data_Scientist_28_high",
    "question_id": "q_Data_Scientist_28",
    "content": "In my previous role at XYZ company, we faced a situation where...\n\nMy task was to...\n\nTo address this, I...\n\nThe outcome was...\n\n",
    "audio_source": null,
    "confidence": 0.95,
    "created_at": "2025-04-03T21:45:16.983687"
  },
  {
    "id": "a_q_Data_Scientist_28_medium",
    "question_id": "q_Data_Scientist_28",
    "content": "To address this, I...\n\n",
    "audio_source": null,
    "confidence": 0.8,
    "created_at": "2025-04-03T21:45:16.985982"
  },
  {
    "id": "a_q_Data_Scientist_28_low",
    "question_id": "q_Data_Scientist_28",
    "content": "",
    "audio_source": null,
    "confidence": 0.6,
    "created_at": "2025-04-03T21:45:16.988231"
  },
  {
    "id": "a_q_Data_Scientist_29_high",
    "question_id": "q_Data_Scientist_29",
    "content": "In my previous role at XYZ company, we faced a situation where...\n\nMy task was to...\n\nTo address this, I...\n\nThe outcome was...\n\n",
    "audio_source": null,
    "confidence": 0.95,
    "created_at": "2025-04-03T21:45:16.990235"
  },
  {
    "id": "a_q_Data_Scientist_29_medium",
    "question_id": "q_Data_Scientist_29",
    "content": "To address this, I...\n\n",
    "audio_source": null,
    "confidence": 0.8,
    "created_at": "2025-04-03T21:45:16.992630"
  },
  {
    "id": "a_q_Data_Scientist_29_low",
    "question_id": "q_Data_Scientist_29",
    "content": "",
    "audio_source": null,
    "confidence": 0.6,
    "created_at": "2025-04-03T21:45:16.995759"
  },
  {
    "id": "a_q_Data_Scientist_30_high",
    "question_id": "q_Data_Scientist_30",
    "content": "In my previous role at XYZ company, we faced a situation where...\n\nMy task was to...\n\nTo address this, I...\n\nThe outcome was...\n\n",
    "audio_source": null,
    "confidence": 0.95,
    "created_at": "2025-04-03T21:45:16.997396"
  },
  {
    "id": "a_q_Data_Scientist_30_medium",
    "question_id": "q_Data_Scientist_30",
    "content": "To address this, I...\n\n",
    "audio_source": null,
    "confidence": 0.8,
    "created_at": "2025-04-03T21:45:17.000491"
  },
  {
    "id": "a_q_Data_Scientist_30_low",
    "question_id": "q_Data_Scientist_30",
    "content": "",
    "audio_source": null,
    "confidence": 0.6,
    "created_at": "2025-04-03T21:45:17.001514"
  },
  {
    "id": "a_q_Data_Scientist_31_high",
    "question_id": "q_Data_Scientist_31",
    "content": "In my previous role at XYZ company, we faced a situation where...\n\nMy task was to...\n\nTo address this, I...\n\nThe outcome was...\n\n",
    "audio_source": null,
    "confidence": 0.95,
    "created_at": "2025-04-03T21:45:17.004388"
  },
  {
    "id": "a_q_Data_Scientist_31_medium",
    "question_id": "q_Data_Scientist_31",
    "content": "To address this, I...\n\n",
    "audio_source": null,
    "confidence": 0.8,
    "created_at": "2025-04-03T21:45:17.006249"
  },
  {
    "id": "a_q_Data_Scientist_31_low",
    "question_id": "q_Data_Scientist_31",
    "content": "",
    "audio_source": null,
    "confidence": 0.6,
    "created_at": "2025-04-03T21:45:17.007836"
  },
  {
    "id": "a_q_Data_Scientist_32_high",
    "question_id": "q_Data_Scientist_32",
    "content": "In my previous role at XYZ company, we faced a situation where...\n\nMy task was to...\n\nTo address this, I...\n\nThe outcome was...\n\n",
    "audio_source": null,
    "confidence": 0.95,
    "created_at": "2025-04-03T21:45:17.011976"
  },
  {
    "id": "a_q_Data_Scientist_32_medium",
    "question_id": "q_Data_Scientist_32",
    "content": "To address this, I...\n\n",
    "audio_source": null,
    "confidence": 0.8,
    "created_at": "2025-04-03T21:45:17.013108"
  },
  {
    "id": "a_q_Data_Scientist_32_low",
    "question_id": "q_Data_Scientist_32",
    "content": "",
    "audio_source": null,
    "confidence": 0.6,
    "created_at": "2025-04-03T21:45:17.016919"
  },
  {
    "id": "a_q_Data_Scientist_33_high",
    "question_id": "q_Data_Scientist_33",
    "content": "In my previous role at XYZ company, we faced a situation where...\n\nMy task was to...\n\nTo address this, I...\n\nThe outcome was...\n\n",
    "audio_source": null,
    "confidence": 0.95,
    "created_at": "2025-04-03T21:45:17.016919"
  },
  {
    "id": "a_q_Data_Scientist_33_medium",
    "question_id": "q_Data_Scientist_33",
    "content": "To address this, I...\n\n",
    "audio_source": null,
    "confidence": 0.8,
    "created_at": "2025-04-03T21:45:17.016919"
  },
  {
    "id": "a_q_Data_Scientist_33_low",
    "question_id": "q_Data_Scientist_33",
    "content": "",
    "audio_source": null,
    "confidence": 0.6,
    "created_at": "2025-04-03T21:45:17.024597"
  },
  {
    "id": "a_q_Data_Scientist_34_high",
    "question_id": "q_Data_Scientist_34",
    "content": "In my previous role at XYZ company, we faced a situation where...\n\nMy task was to...\n\nTo address this, I...\n\nThe outcome was...\n\n",
    "audio_source": null,
    "confidence": 0.95,
    "created_at": "2025-04-03T21:45:17.027129"
  },
  {
    "id": "a_q_Data_Scientist_34_medium",
    "question_id": "q_Data_Scientist_34",
    "content": "To address this, I...\n\n",
    "audio_source": null,
    "confidence": 0.8,
    "created_at": "2025-04-03T21:45:17.029667"
  },
  {
    "id": "a_q_Data_Scientist_34_low",
    "question_id": "q_Data_Scientist_34",
    "content": "",
    "audio_source": null,
    "confidence": 0.6,
    "created_at": "2025-04-03T21:45:17.033191"
  }
]